<?xml version="1.0" encoding="UTF-8"?>
<DEFECTS>
  <DEFECT>
    <SFA>
      <FILEPATH>c:\users\roman\documents\hs21\informatik1\projekte_vs17\semesteraufgabe\semesteraufgabe\semesteraufgabe</FILEPATH>
      <FILENAME>quelle.cpp</FILENAME>
      <LINE>9</LINE>
      <COLUMN>4</COLUMN>
    </SFA>
    <DEFECTCODE>6262</DEFECTCODE>
    <DESCRIPTION>Die Funktion verwendet "848008" Bytes vom Stapel und überschreitet /analyze:stacksize "16384". Verschieben Sie einige Daten auf den Heap.</DESCRIPTION>
    <FUNCTION>main</FUNCTION>
    <DECORATED>main</DECORATED>
    <FUNCLINE>9</FUNCLINE>
    <PATH></PATH>
  </DEFECT>
  <DEFECT>
    <SFA>
      <FILEPATH>c:\users\roman\documents\hs21\informatik1\projekte_vs17\semesteraufgabe\semesteraufgabe\semesteraufgabe</FILEPATH>
      <FILENAME>quelle.cpp</FILENAME>
      <LINE>22</LINE>
      <COLUMN>7</COLUMN>
    </SFA>
    <DEFECTCODE>6031</DEFECTCODE>
    <DESCRIPTION>Rückgabewert wird ignoriert: "scanf".</DESCRIPTION>
    <FUNCTION>main</FUNCTION>
    <DECORATED>main</DECORATED>
    <FUNCLINE>9</FUNCLINE>
    <PATH></PATH>
  </DEFECT>
  <DEFECT>
    <SFA>
      <FILEPATH>c:\users\roman\documents\hs21\informatik1\projekte_vs17\semesteraufgabe\semesteraufgabe\semesteraufgabe</FILEPATH>
      <FILENAME>quelle.cpp</FILENAME>
      <LINE>28</LINE>
      <COLUMN>10</COLUMN>
    </SFA>
    <DEFECTCODE>6031</DEFECTCODE>
    <DESCRIPTION>Rückgabewert wird ignoriert: "getchar".</DESCRIPTION>
    <FUNCTION>main</FUNCTION>
    <DECORATED>main</DECORATED>
    <FUNCLINE>9</FUNCLINE>
    <PATH></PATH>
  </DEFECT>
  <DEFECT>
    <SFA>
      <FILEPATH>c:\users\roman\documents\hs21\informatik1\projekte_vs17\semesteraufgabe\semesteraufgabe\semesteraufgabe</FILEPATH>
      <FILENAME>quelle.cpp</FILENAME>
      <LINE>35</LINE>
      <COLUMN>10</COLUMN>
    </SFA>
    <DEFECTCODE>6031</DEFECTCODE>
    <DESCRIPTION>Rückgabewert wird ignoriert: "getchar".</DESCRIPTION>
    <FUNCTION>main</FUNCTION>
    <DECORATED>main</DECORATED>
    <FUNCLINE>9</FUNCLINE>
    <PATH></PATH>
  </DEFECT>
  <DEFECT>
    <SFA>
      <FILEPATH>c:\users\roman\documents\hs21\informatik1\projekte_vs17\semesteraufgabe\semesteraufgabe\semesteraufgabe</FILEPATH>
      <FILENAME>quelle.cpp</FILENAME>
      <LINE>47</LINE>
      <COLUMN>10</COLUMN>
    </SFA>
    <DEFECTCODE>6031</DEFECTCODE>
    <DESCRIPTION>Rückgabewert wird ignoriert: "getchar".</DESCRIPTION>
    <FUNCTION>main</FUNCTION>
    <DECORATED>main</DECORATED>
    <FUNCLINE>9</FUNCLINE>
    <PATH></PATH>
  </DEFECT>
  <DEFECT>
    <SFA>
      <FILEPATH>c:\users\roman\documents\hs21\informatik1\projekte_vs17\semesteraufgabe\semesteraufgabe\semesteraufgabe</FILEPATH>
      <FILENAME>quelle.cpp</FILENAME>
      <LINE>54</LINE>
      <COLUMN>10</COLUMN>
    </SFA>
    <DEFECTCODE>6031</DEFECTCODE>
    <DESCRIPTION>Rückgabewert wird ignoriert: "getchar".</DESCRIPTION>
    <FUNCTION>main</FUNCTION>
    <DECORATED>main</DECORATED>
    <FUNCLINE>9</FUNCLINE>
    <PATH></PATH>
  </DEFECT>
  <DEFECT>
    <SFA>
      <FILEPATH>c:\users\roman\documents\hs21\informatik1\projekte_vs17\semesteraufgabe\semesteraufgabe\semesteraufgabe</FILEPATH>
      <FILENAME>quelle.cpp</FILENAME>
      <LINE>60</LINE>
      <COLUMN>10</COLUMN>
    </SFA>
    <DEFECTCODE>6031</DEFECTCODE>
    <DESCRIPTION>Rückgabewert wird ignoriert: "getchar".</DESCRIPTION>
    <FUNCTION>main</FUNCTION>
    <DECORATED>main</DECORATED>
    <FUNCLINE>9</FUNCLINE>
    <PATH></PATH>
  </DEFECT>
  <DEFECT>
    <SFA>
      <FILEPATH>c:\users\roman\documents\hs21\informatik1\projekte_vs17\semesteraufgabe\semesteraufgabe\semesteraufgabe</FILEPATH>
      <FILENAME>quelle.cpp</FILENAME>
      <LINE>73</LINE>
      <COLUMN>10</COLUMN>
    </SFA>
    <DEFECTCODE>6031</DEFECTCODE>
    <DESCRIPTION>Rückgabewert wird ignoriert: "getchar".</DESCRIPTION>
    <FUNCTION>main</FUNCTION>
    <DECORATED>main</DECORATED>
    <FUNCLINE>9</FUNCLINE>
    <PATH></PATH>
  </DEFECT>
  <DEFECT>
    <SFA>
      <FILEPATH>c:\users\roman\documents\hs21\informatik1\projekte_vs17\semesteraufgabe\semesteraufgabe\semesteraufgabe</FILEPATH>
      <FILENAME>quelle.cpp</FILENAME>
      <LINE>73</LINE>
      <COLUMN>21</COLUMN>
    </SFA>
    <DEFECTCODE>6031</DEFECTCODE>
    <DESCRIPTION>Rückgabewert wird ignoriert: "getchar".</DESCRIPTION>
    <FUNCTION>main</FUNCTION>
    <DECORATED>main</DECORATED>
    <FUNCLINE>9</FUNCLINE>
    <PATH></PATH>
  </DEFECT>
  <DEFECT>
    <SFA>
      <FILEPATH>c:\users\roman\documents\hs21\informatik1\projekte_vs17\semesteraufgabe\semesteraufgabe\semesteraufgabe</FILEPATH>
      <FILENAME>quelle.cpp</FILENAME>
      <LINE>78</LINE>
      <COLUMN>8</COLUMN>
    </SFA>
    <DEFECTCODE>6031</DEFECTCODE>
    <DESCRIPTION>Rückgabewert wird ignoriert: "getchar".</DESCRIPTION>
    <FUNCTION>main</FUNCTION>
    <DECORATED>main</DECORATED>
    <FUNCLINE>9</FUNCLINE>
    <PATH></PATH>
  </DEFECT>
</DEFECTS>